telemetry/__init__.py
telemetry/config.py
telemetry/logging.py
telemetry/metrics.py
telemetry/traces.py
polympiads_telemetry-1.0.0.dist-info/LICENSE
polympiads_telemetry-1.0.0.dist-info/METADATA
polympiads_telemetry-1.0.0.dist-info/WHEEL
polympiads_telemetry-1.0.0.dist-info/top_level.txt
polympiads_telemetry-1.0.0.dist-info/RECORD
